jikanpy/__init__.py
jikanpy/aiojikan.py
jikanpy/exceptions.py
jikanpy/jikan.py
jikanpy/py.typed
jikanpy/utils.py
jikanpy-4.3.2.dist-info/LICENSE
jikanpy-4.3.2.dist-info/METADATA
jikanpy-4.3.2.dist-info/WHEEL
jikanpy-4.3.2.dist-info/top_level.txt
jikanpy-4.3.2.dist-info/RECORD
