Metadata-Version: 2.1
Name: jikanpy
Version: 4.3.2
Summary: Python wrapper for the Jikan API
Home-page: https://github.com/abhinavk99/jikanpy
Author: Abhinav Kasamsetty
Author-email: abhinavkasamsetty@gmail.com
License: MIT
Keywords: jikan,jikanpy,api,myanimelist
Platform: UNKNOWN
Classifier: Programming Language :: Python :: 3
Classifier: Programming Language :: Python :: 3.6
Classifier: Programming Language :: Python :: 3.7
Classifier: License :: OSI Approved :: MIT License
Requires-Python: >=3.6
